thinagents/__init__.py
thinagents/frontend/.gitignore
thinagents/frontend/.npmrc
thinagents/frontend/.prettierignore
thinagents/frontend/.prettierrc
thinagents/frontend/README.md
thinagents/frontend/components.json
thinagents/frontend/eslint.config.js
thinagents/frontend/package.json
thinagents/frontend/svelte.config.js
thinagents/frontend/tsconfig.json
thinagents/frontend/vite.config.ts
thinagents/frontend/src/app.css
thinagents/frontend/src/app.d.ts
thinagents/frontend/src/app.html
thinagents/frontend/src/lib/index.ts
thinagents/frontend/src/lib/utils.ts
thinagents/frontend/src/lib/assets/favicon.svg
thinagents/frontend/src/lib/components/app-sidebar.svelte
thinagents/frontend/src/lib/components/nav-main.svelte
thinagents/frontend/src/lib/components/nav-projects.svelte
thinagents/frontend/src/lib/components/nav-user.svelte
thinagents/frontend/src/lib/components/team-switcher.svelte
thinagents/frontend/src/lib/components/prompt-kit/message/Message.svelte
thinagents/frontend/src/lib/components/prompt-kit/message/MessageAction.svelte
thinagents/frontend/src/lib/components/prompt-kit/message/MessageActions.svelte
thinagents/frontend/src/lib/components/prompt-kit/message/MessageAvatar.svelte
thinagents/frontend/src/lib/components/prompt-kit/message/MessageContent.svelte
thinagents/frontend/src/lib/components/prompt-kit/message/index.ts
thinagents/frontend/src/lib/components/prompt-kit/message/message-context.svelte.ts
thinagents/frontend/src/lib/components/prompt-kit/prompt-input/PromptInput.svelte
thinagents/frontend/src/lib/components/prompt-kit/prompt-input/PromptInputAction.svelte
thinagents/frontend/src/lib/components/prompt-kit/prompt-input/PromptInputActions.svelte
thinagents/frontend/src/lib/components/prompt-kit/prompt-input/PromptInputTextarea.svelte
thinagents/frontend/src/lib/components/prompt-kit/prompt-input/index.ts
thinagents/frontend/src/lib/components/prompt-kit/prompt-input/prompt-input-context.svelte.ts
thinagents_web-0.0.1.dist-info/METADATA
thinagents_web-0.0.1.dist-info/WHEEL
thinagents_web-0.0.1.dist-info/top_level.txt
thinagents_web-0.0.1.dist-info/RECORD
