Metadata-Version: 2.4
Name: ThinAgents_Web
Version: 0.0.1
Summary: Web application for ThinAgents
Home-page: https://github.com/PrabhuKiran8790/thinagents_web
Author: Prabhu Kiran Konda
License: MIT
Project-URL: Homepage, https://github.com/PrabhuKiran8790/thinagents
Keywords: AI,LLM,Agentic AI,AI Agents
Classifier: Programming Language :: Python :: 3
Classifier: License :: OSI Approved :: MIT License
Classifier: Operating System :: OS Independent
Requires-Python: >=3.10
Requires-Dist: thinagents>=0.0.16
Requires-Dist: fastapi>=0.104.0
Requires-Dist: uvicorn>=0.24.0
Dynamic: home-page
Dynamic: requires-python
